shapepy/__init__.py
shapepy/analytic/__init__.py
shapepy/analytic/base.py
shapepy/analytic/bezier.py
shapepy/analytic/polynomial.py
shapepy/analytic/tools.py
shapepy/bool2d/__init__.py
shapepy/bool2d/base.py
shapepy/bool2d/boolean.py
shapepy/bool2d/primitive.py
shapepy/bool2d/shape.py
shapepy/common.py
shapepy/geometry/__init__.py
shapepy/geometry/base.py
shapepy/geometry/box.py
shapepy/geometry/concatenate.py
shapepy/geometry/factory.py
shapepy/geometry/integral.py
shapepy/geometry/intersection.py
shapepy/geometry/jordancurve.py
shapepy/geometry/piecewise.py
shapepy/geometry/point.py
shapepy/geometry/segment.py
shapepy/geometry/unparam.py
shapepy/plot/__init__.py
shapepy/plot/plot.py
shapepy/scalar/__init__.py
shapepy/scalar/angle.py
shapepy/scalar/nodes_sample.py
shapepy/scalar/quadrature.py
shapepy/scalar/reals.py
shapepy/tools.py
shapepy-1.1.7.dist-info/LICENSE.md
shapepy-1.1.7.dist-info/METADATA
shapepy-1.1.7.dist-info/WHEEL
shapepy-1.1.7.dist-info/RECORD
