Metadata-Version: 2.3
Name: shapepy
Version: 1.1.7
Summary: Geometric 2D library
Author: Carlos Adir
Author-email: carlos.adir.leite@gmail.com
Requires-Python: >=3.9,<4.0
Classifier: Programming Language :: Python :: 3
Classifier: Programming Language :: Python :: 3.9
Classifier: Programming Language :: Python :: 3.10
Classifier: Programming Language :: Python :: 3.11
Classifier: Programming Language :: Python :: 3.12
Classifier: Programming Language :: Python :: 3.13
Provides-Extra: mesh
Requires-Dist: matplotlib (>=3.4.0,<4.0.0)
Requires-Dist: numpy (>=1.0.0,<2.0.0)
Requires-Dist: pynurbs (>=1.0.7,<2.0.0)
Requires-Dist: rbool (>=0.0.4,<0.0.5)
Requires-Dist: setuptools ; python_version >= "3.12"
